rtoolz/__init__.py
rtoolz/parallelize.py
rtoolz-0.1.dist-info/LICENSE
rtoolz-0.1.dist-info/METADATA
rtoolz-0.1.dist-info/WHEEL
rtoolz-0.1.dist-info/top_level.txt
rtoolz-0.1.dist-info/RECORD
