Metadata-Version: 2.1
Name: rtoolz
Version: 0.1
Summary: A collection of random tools I find useful.
Home-page: http://github.com/chrisfinlay/rtoolz
Author: Chris Finlay
Author-email: chrisfinlay93@gmail.com
License: MIT
Platform: UNKNOWN
